setup.py
bigquerytest/__init__.py
bigquerytest/table.py
bigquerytest/testcase.py
bigquerytest.egg-info/PKG-INFO
bigquerytest.egg-info/SOURCES.txt
bigquerytest.egg-info/dependency_links.txt
bigquerytest.egg-info/requires.txt
bigquerytest.egg-info/top_level.txt
test/test_table.py
test/test_testcase.py