Metadata-Version: 1.0
Name: bigquerytest
Version: 0.1.5
Summary: unittest TestCase with BigQuery table mocks in human-readable format
Home-page: UNKNOWN
Author: Andreas Jansson
Author-email: andreas@jansson.me.uk
License: MIT
Platform: UNKNOWN
